sc2_datasets/__init__.py
sc2_datasets/available_replaypacks.py
sc2_datasets/lightning/__init__.py
sc2_datasets/lightning/datamodules/__init__.py
sc2_datasets/lightning/datamodules/sc2_datamodule.py
sc2_datasets/lightning/datamodules/sc2_replaypack_datamodule.py
sc2_datasets/lightning/sc2_egset_datamodule.py
sc2_datasets/replay_data/__init__.py
sc2_datasets/replay_data/sc2_replay_data.py
sc2_datasets/replay_parser/__init__.py
sc2_datasets/replay_parser/details/__init__.py
sc2_datasets/replay_parser/details/details.py
sc2_datasets/replay_parser/game_events/__init__.py
sc2_datasets/replay_parser/game_events/events/__init__.py
sc2_datasets/replay_parser/game_events/events/camera_save.py
sc2_datasets/replay_parser/game_events/events/camera_update.py
sc2_datasets/replay_parser/game_events/events/cmd.py
sc2_datasets/replay_parser/game_events/events/cmd_update_target_point.py
sc2_datasets/replay_parser/game_events/events/cmd_update_target_unit.py
sc2_datasets/replay_parser/game_events/events/command_manager_state.py
sc2_datasets/replay_parser/game_events/events/control_group_update.py
sc2_datasets/replay_parser/game_events/events/game_user_leave.py
sc2_datasets/replay_parser/game_events/events/nested/__init__.py
sc2_datasets/replay_parser/game_events/events/nested/delta.py
sc2_datasets/replay_parser/game_events/events/nested/target_2d.py
sc2_datasets/replay_parser/game_events/events/nested/target_3d.py
sc2_datasets/replay_parser/game_events/events/nested/target_unit.py
sc2_datasets/replay_parser/game_events/events/selection_delta.py
sc2_datasets/replay_parser/game_events/events/user_options.py
sc2_datasets/replay_parser/game_events/game_event.py
sc2_datasets/replay_parser/game_events/game_events_parser.py
sc2_datasets/replay_parser/header/__init__.py
sc2_datasets/replay_parser/header/header.py
sc2_datasets/replay_parser/init_data/__init__.py
sc2_datasets/replay_parser/init_data/game_description.py
sc2_datasets/replay_parser/init_data/game_options.py
sc2_datasets-1.0.2.dist-info/LICENSE
sc2_datasets-1.0.2.dist-info/WHEEL
sc2_datasets-1.0.2.dist-info/METADATA
sc2_datasets-1.0.2.dist-info/RECORD
