Metadata-Version: 2.1
Name: sc2-datasets
Version: 1.0.2
Summary: Library providing PyTorch and PyTorch Lightning API for pre-processed StarCraft II dataset SC2EGSetDataset and other datasets.
License: GNU General Public License v3.0
Author: Andrzej Białecki
Requires-Python: >=3.10,<4.0
Classifier: License :: Other/Proprietary License
Classifier: Programming Language :: Python :: 3
Classifier: Programming Language :: Python :: 3.10
Requires-Dist: pandas (>=1.4.3,<2.0.0)
Requires-Dist: pytorch-lightning (>=1.6.5,<2.0.0)
Requires-Dist: tqdm (>=4.64.0,<5.0.0)
